data_aug_4_tsc/__init__.py
data_aug_4_tsc-0.0.1.dist-info/licenses/LICENSE
data_aug_4_tsc-0.0.1.dist-info/METADATA
data_aug_4_tsc-0.0.1.dist-info/WHEEL
data_aug_4_tsc-0.0.1.dist-info/top_level.txt
data_aug_4_tsc-0.0.1.dist-info/RECORD
