Metadata-Version: 2.4
Name: data-aug-4-tsc
Version: 0.0.1
Summary: Data Augmentation for Time series Data: A Review
Author-email: Ali Ismail-Fawaz <ali-el-hadi.ismail-fawaz@uha.fr>, Maxime Devanne <maxime.devanne@uha.fr>, Stefano Berretti <stefano.berretti@unifi.it>, Jonathan Weber <jonathan.weber@uha.fr>, Germain Forestier <germain.forestier@uha.fr>
Maintainer-email: Ali Ismail-Fawaz <ali-el-hadi.ismail-fawaz@uha.fr>
License: GPL-3.0-only
Project-URL: Homepage, https://github.com/MSD-IRIMAS/Data-Augmentation-4-TSC/
Project-URL: Repository, https://github.com/MSD-IRIMAS/Data-Augmentation-4-TSC
Project-URL: Download, https://pypi.org/project/data-aug-4-tsc/#files
Keywords: data-science,machine-learning,data-mining,time-series,classification,time-series-analysis,time-series-classification,time-series-augmentation,data-augmentation
Classifier: Development Status :: 4 - Beta
Classifier: Intended Audience :: Developers
Classifier: License :: OSI Approved :: GNU General Public License v3 (GPLv3)
Classifier: Programming Language :: Python :: 3
Classifier: Programming Language :: Python :: 3.10
Classifier: Programming Language :: Python :: 3.11
Classifier: Programming Language :: Python :: 3.12
Requires-Python: >=3.10
License-File: LICENSE
Requires-Dist: tensorflow==2.16.1
Requires-Dist: keras==3.6.0
Requires-Dist: numpy<2.1.0,>=1.21.0
Requires-Dist: aeon==1.0.0
Requires-Dist: hydra-core==1.3.2
Requires-Dist: omegaconf==2.3.0
Requires-Dist: pandas==2.2.0
Requires-Dist: matplotlib==3.10.0
Requires-Dist: numba==0.60.0
Provides-Extra: dev
Requires-Dist: black; extra == "dev"
Requires-Dist: flake8; extra == "dev"
Requires-Dist: mypy; extra == "dev"
Requires-Dist: pytest; extra == "dev"
Requires-Dist: pytest-cov; extra == "dev"
Requires-Dist: pytest-xdist; extra == "dev"
Requires-Dist: pytest-timeout; extra == "dev"
Requires-Dist: pytest-rerunfailures; extra == "dev"
Requires-Dist: pre-commit; extra == "dev"
Dynamic: license-file
